LICENSE
MANIFEST.in
README.md
ez_setup.py
nebgb.py
setup.py
nebgb.egg-info/PKG-INFO
nebgb.egg-info/SOURCES.txt
nebgb.egg-info/dependency_links.txt
nebgb.egg-info/not-zip-safe
nebgb.egg-info/top_level.txt
test/000-locus-test.py
test/010-keywords-test.py
test/011-keywords-test.py
test/020-location-test.py
test/030-features-test.py
test/031-features-test.py
test/040-sequence-test.py
test/050-base-count-test.py
test/060-regression-test.py
test/t.py
test/data/bad-qualifiers-1.gb
test/data/bad-qualifiers-2.gb
test/data/bad-qualifiers-3.gb
test/data/bad-reference.gb
test/data/base-counts-1.gb
test/data/base-counts-2.gb
test/data/base-counts-3.gb
test/data/base-counts-4.gb
test/data/bond.gb
test/data/contig.gb
test/data/empty-seq-line.gb
test/data/fuzzy.gb
test/data/keywords.gb
test/data/multiple-records.gb
test/data/one-of.gb
test/data/order.gb
test/data/primary-1.gb
test/data/primary-2.gb
test/data/primary-3.gb
test/data/segment.gb
test/data/simple-1.gb
test/data/simple-2.gb
test/data/stem-loop.gb
test/regressions/__init__.py
test/regressions/bad-qualifiers-1-0.py
test/regressions/bad-qualifiers-2-0.py
test/regressions/bad-qualifiers-3-0.py
test/regressions/bad-reference-0.py
test/regressions/base-counts-1-0.py
test/regressions/base-counts-2-0.py
test/regressions/base-counts-3-0.py
test/regressions/base-counts-4-0.py
test/regressions/bond-0.py
test/regressions/contig-0.py
test/regressions/empty-seq-line-0.py
test/regressions/fuzzy-0.py
test/regressions/keywords-0.py
test/regressions/multiple-records-0.py
test/regressions/multiple-records-1.py
test/regressions/multiple-records-2.py
test/regressions/multiple-records-3.py
test/regressions/multiple-records-4.py
test/regressions/multiple-records-5.py
test/regressions/one-of-0.py
test/regressions/order-0.py
test/regressions/primary-1-0.py
test/regressions/primary-2-0.py
test/regressions/primary-3-0.py
test/regressions/segment-0.py
test/regressions/simple-1-0.py
test/regressions/simple-2-0.py
test/regressions/stem-loop-0.py